opencastapi/__init__.py
opencastapi/bootstrap.py
opencastapi/adapters/__init__.py
opencastapi/adapters/config.py
opencastapi/domain/__init__.py
opencastapi/domain/call.py
opencastapi/domain/config.py
opencastapi/domain/events.py
opencastapi/entrypoints/__init__.py
opencastapi/entrypoints/api.py
opencastapi/service_layer/__init__.py
opencastapi/service_layer/services.py
opencastapi-1.0.11.dist-info/LICENSE.txt
opencastapi-1.0.11.dist-info/METADATA
opencastapi-1.0.11.dist-info/WHEEL
opencastapi-1.0.11.dist-info/top_level.txt
opencastapi-1.0.11.dist-info/RECORD
