Metadata-Version: 2.1
Name: opencastapi
Version: 1.0.11
Summary: Provides object-oriented Opencast API call support.
Home-page: https://git.bellavistakappl.at/namespace/py_opencastapi
Author: Jonathan L. Komar
Author-email: komar.jonathan@gmail.com
License: MIT
Platform: UNKNOWN
Classifier: License :: OSI Approved :: MIT License
Classifier: Programming Language :: Python :: 3
License-File: LICENSE.txt
Requires-Dist: functionaljlk (>=1.0.4)
Requires-Dist: requests
